setup.py
jylab/JYFunctoin.py
jylab/__init__.py
jylab.egg-info/PKG-INFO
jylab.egg-info/SOURCES.txt
jylab.egg-info/dependency_links.txt
jylab.egg-info/requires.txt
jylab.egg-info/top_level.txt