Metadata-Version: 1.0
Name: jylab
Version: 0.0.3
Summary: isoweek calculation and so on
Home-page: https://github.com/ricky2634/jylab
Author: kimjeongyeon
Author-email: ricky2634@naver.com
License: MIT
Keywords: calendar,isoweek,listsum
Platform: UNKNOWN
